totindex/__init__.py
totindex/main.py
totindex/data/TOT_Experimental_Data.xlsx
totindex-1.0.3.dist-info/METADATA
totindex-1.0.3.dist-info/WHEEL
totindex-1.0.3.dist-info/entry_points.txt
totindex-1.0.3.dist-info/top_level.txt
totindex-1.0.3.dist-info/RECORD
